[{"path":"./common/images/logo.png","key":"image_logo","name":"logo.png","edit":false},{"path":"./resources/assets/images/1.png","key":"image_1","name":"1.png","edit":false},{"path":"./resources/assets/images/2.png","key":"image_2","name":"2.png","edit":false},{"path":"./resources/assets/images/3.png","key":"image_3","name":"3.png","edit":false},{"path":"./resources/assets/images/4.png","key":"image_4","name":"4.png","edit":false},{"path":"./resources/assets/images/5.png","key":"image_5","name":"5.png","edit":false},{"path":"./resources/assets/images/6.png","key":"image_6","name":"6.png","edit":false},{"path":"./resources/assets/images/7.png","key":"image_7","name":"7.png","edit":false},{"path":"./resources/assets/images/8.png","key":"image_8","name":"8.png","edit":false},{"path":"./resources/assets/images/9.png","key":"image_9","name":"9.png","edit":false},{"path":"./resources/assets/images/btn1.png","key":"image_btn1","name":"btn1.png","edit":false},{"path":"./resources/assets/images/bg.png","key":"image_bg","name":"bg.png","edit":false},{"path":"./resources/assets/images/btn2.png","key":"image_btn2","name":"btn2.png","edit":false},{"path":"./resources/assets/images/btn3.png","key":"image_btn3","name":"btn3.png","edit":false},{"path":"./resources/assets/images/num1.png","key":"image_num1","name":"num1.png","edit":false},{"path":"./resources/assets/images/gz.png","key":"image_gz","name":"gz.png","edit":false},{"path":"./resources/assets/images/num2.png","key":"image_num2","name":"num2.png","edit":false},{"path":"./resources/assets/images/num3.png","key":"image_num3","name":"num3.png","edit":false},{"path":"./resources/assets/images/touming.png","key":"image_touming","name":"touming.png","edit":false},{"path":"./resources/assets/images/num4.png","key":"image_num4","name":"num4.png","edit":false},{"path":"./resources/assets/audios/click.mp3","key":"audio_click","name":"click.mp3","edit":false},{"path":"./resources/assets/audios/dragTrue.mp3","key":"audio_dragTrue","name":"dragTrue.mp3","edit":false},{"path":"./resources/assets/audios/error.mp3","key":"audio_error","name":"error.mp3","edit":false},{"path":"./resources/assets/audios/kacha.mp3","key":"audio_kacha","name":"kacha.mp3","edit":false},{"path":"./resources/assets/audios/true.mp3","key":"audio_true","name":"true.mp3","edit":false},{"path":"./resources/animation/combine.json","key":"animation_1","name":"1.json","edit":false,"level":"1"}]